LICENSE
sageup/__init__.py
sageup-0.1.2.dist-info/entry_points.txt
sageup-0.1.2.dist-info/LICENSE
sageup-0.1.2.dist-info/WHEEL
sageup-0.1.2.dist-info/METADATA
sageup-0.1.2.dist-info/RECORD
